dtl_siamese_network/__init__.py
dtl_siamese_network/feature_extraction.py
dtl_siamese_network/data/__init__.py
dtl_siamese_network/data/datasets.py
dtl_siamese_network/data/transforms.py
dtl_siamese_network/models/__init__.py
dtl_siamese_network/models/model_hg.py
dtl_siamese_network/models/networks.py
DTLSiameseNetwork-0.0.8.dist-info/LICENSE
DTLSiameseNetwork-0.0.8.dist-info/METADATA
DTLSiameseNetwork-0.0.8.dist-info/WHEEL
DTLSiameseNetwork-0.0.8.dist-info/top_level.txt
DTLSiameseNetwork-0.0.8.dist-info/RECORD
